edabox/__init__.py
edabox/core/__init__.py
edabox/core/box.py
tests/__init__.py
tests/test_box.py
tests/test_process_frame.py
tests/test_syntax.py
edabox-1.0.0.dist-info/LICENSE
edabox-1.0.0.dist-info/METADATA
edabox-1.0.0.dist-info/WHEEL
edabox-1.0.0.dist-info/top_level.txt
edabox-1.0.0.dist-info/RECORD
