Metadata-Version: 2.1
Name: edabox
Version: 1.0.0
Summary: Python Library to Gain Insight into Datasets
Home-page: https://github.com/poushalimukherjee/edabox
Author: Poushali Mukherjee
License: MIT
License-File: LICENSE
Requires-Dist: pandas
Requires-Dist: colorama
Requires-Dist: matplotlib
Requires-Dist: seaborn
